pab_cli/__init__.py
pab_cli/auth.py
pab_cli/cli.py
pab_cli/config.py
pab_cli/deploy.py
pab_cli/exceptions.py
pab_cli/http_client.py
pab_cli/package.py
pab_cli/utils.py
pab_cli/validator.py
pab_cli-0.2.4.dist-info/licenses/LICENSE
pab_cli-0.2.4.dist-info/METADATA
pab_cli-0.2.4.dist-info/WHEEL
pab_cli-0.2.4.dist-info/entry_points.txt
pab_cli-0.2.4.dist-info/top_level.txt
pab_cli-0.2.4.dist-info/RECORD
