Metadata-Version: 2.4
Name: pab-cli
Version: 0.2.4
Summary: A command-line tool for deploying Scrapy spiders to APCloudy
Home-page: https://github.com/fawadss1/pab-cli
Author: Fawad Ali
Author-email: Fawad Ali <Fawadstar6@gmail.com>
License: MIT
Project-URL: Homepage, https://github.com/fawadss1/pab-cli
Project-URL: Documentation, https://github.com/fawadss1/pab-cli#readme
Project-URL: Repository, https://github.com/fawadss1/pab-cli
Project-URL: Bug Tracker, https://github.com/fawadss1/pab-cli/issues
Keywords: scrapy,spider,deployment,cloud,apcloudy
Classifier: Development Status :: 4 - Beta
Classifier: Intended Audience :: Developers
Classifier: License :: OSI Approved :: MIT License
Classifier: Operating System :: OS Independent
Classifier: Programming Language :: Python :: 3
Classifier: Programming Language :: Python :: 3.7
Classifier: Programming Language :: Python :: 3.8
Classifier: Programming Language :: Python :: 3.9
Classifier: Programming Language :: Python :: 3.10
Classifier: Programming Language :: Python :: 3.11
Classifier: Topic :: Internet :: WWW/HTTP
Classifier: Topic :: Software Development :: Libraries :: Application Frameworks
Requires-Python: >=3.7
License-File: LICENSE
Requires-Dist: click>=8.2.1
Requires-Dist: requests>=2.32.4
Requires-Dist: scrapy>=2.13.3
Requires-Dist: pyyaml>=6.0.2
Requires-Dist: colorama>=0.4.6
Requires-Dist: tabulate>=0.9.0
Requires-Dist: packaging>=25.0
Dynamic: author
Dynamic: home-page
Dynamic: license-file
Dynamic: requires-python
